Metadata-Version: 1.2
Name: gram-scanner
Version: 1.0.1
Summary: A command line interface of Ionian University's Gram-Web
Home-page: https://github.com/nickgarlis/gram-scanner
Author: Nick Garlis
Author-email: nickgarlis@gmail.com
License: MIT
Keywords: Ionian University,Gram-Webgram-scanner
Platform: UNKNOWN
Classifier: Development Status :: 5 - Production/Stable
Classifier: Programming Language :: Python :: 3
Classifier: Programming Language :: Python :: 3.2
Classifier: Programming Language :: Python :: 3.3
Classifier: Programming Language :: Python :: 3.4
Classifier: Programming Language :: Python :: 3.6
Requires-Python: >=3
